dotnet_generate.py
dotnet_generate-0.5.0.dist-info/LICENSE
dotnet_generate-0.5.0.dist-info/METADATA
dotnet_generate-0.5.0.dist-info/WHEEL
dotnet_generate-0.5.0.dist-info/entry_points.txt
dotnet_generate-0.5.0.dist-info/top_level.txt
dotnet_generate-0.5.0.dist-info/RECORD
