Metadata-Version: 2.1
Name: dotnet-generate
Version: 0.5.0
Summary: Tool for generating dotnet code
Home-page: https://gitlab.com/eskumu/dotnet-generate
Author: Kristjan Tärk
Author-email: kristjan.tark@eesti.ee
License: MIT
Platform: UNKNOWN
Classifier: Programming Language :: Python :: 3
Classifier: Environment :: Console
Classifier: License :: OSI Approved :: MIT License
Classifier: Operating System :: OS Independent
Requires-Dist: Click
